{
  "apartments" : {
    "aptId" : {
      "city" : "ashdod",
      "description" : "some details will be here",
      "floor" : 1,
      "isRented" : true,
      "leasedOn" : "1.1.1990",
      "maxLease" : 0,
      "minLease" : 1,
      "ownerId" : 1234,
      "pictures" : "path",
      "price" : "150$",
      "street" : "something",
      "streetNum" : 5,
      "studentId" : 12345,
      "zip" : 99999
    }
  },
  "orders" : {
    "orderid" : {
      "aptId" : 123,
      "landlordId" : 12345,
      "orderDate" : "1.1.1990",
      "rentingTime" : "1 month",
      "studentId" : 12345678,
      "totSum" : "100$"
    }
  },
  "ratings" : {
    "aptId" : {
      "landlordId" : 123456,
      "studentId" : "1234,1234,12345",
      "totalRating" : 5
    }
  },
  "reviews" : {
    "reviewId" : {
      "aptId" : 123,
      "aptOwner" : 12345,
      "rating" : 5,
      "reviewMsg" : "The review up to aobut 140 characters",
      "studentId" : 12345678,
      "totalRating" : "ratingAptID"
    }
  },
  "users" : [ {
    "academicLoc" : "Ashdod",
    "academy" : "SCE",
    "cId" : "none",
    "cPhone" : "none",
    "cname" : "none",
    "dBirth" : "20.9.1989",
    "email" : "kostyve@ac.sce.il",
    "firstName" : "Kostya",
    "gender" : "male",
    "id" : 12345678,
    "landlord" : false,
    "lastName" : "Varenye",
    "phone" : "05455555555",
    "renterId" : "none",
    "student" : true
  } ]
}
